{"metadata": {"upload_type": "publication", "publication_type": "conferencepaper", "publication_date": "13.02.2017", "title": "PaLaFra \u2013 Entwicklung einer Annotationsumgebung f\u00fcr ein diachrones Korpus sp\u00e4tlateinischer und altfranz\u00f6sischer Texte", "creators": [{"name": "D\u00f6hling, Lars", "affiliation": "Universit\u00e4t Regensburg, Deutschland"}, {"name": "Burghardt, Manuel", "affiliation": "Universit\u00e4t Regensburg, Deutschland"}, {"name": "Wolff, Christian", "affiliation": "Universit\u00e4t Regensburg, Deutschland"}], "description": "A single abstract from the DHd-2017 Book of Abstracts.", "access_right": "open", "license": "cc-by", "doi": "", "keywords": ["poster"], "contributors": [{"name": "Helling, Patrick", "affiliation": "Digital Humanities im deutschsprachigen Raum e.V.", "type": "DataCurator"}], "communities": [{"identifier": "dhd"}], "conference_title": "DHd 2017 - Digitale Nachhaltigkeit. 4. Tagung des Verbands \"Digital Humanities im deutschsprachigen Raum\"", "conference_acronym": "DHd 2017", "conference_dates": "13.02.2017-18.02.2017", "conference_place": "Bern", "conference_url": "https://dhd2015.uni-graz.at/de/"}}